[
    {
        "id": "rec_test_123",
        "rating": 1,
        "comment": "Provided good actionable steps during testing."
    },
    {
        "id": "rec_test_123",
        "rating": 1,
        "comment": "Provided good actionable steps during testing."
    },
    {
        "id": "rec_test_123",
        "rating": 1,
        "comment": "Provided good actionable steps during testing."
    },
    {
        "id": "abc",
        "rating": 1,
        "comment": "ok"
    },
    {
        "id": "x",
        "rating": 5,
        "comment": ""
    },
    {
        "id": "x",
        "rating": 0,
        "comment": ""
    },
    {
        "id": "x",
        "rating": -999,
        "comment": ""
    },
    {
        "id": "19bb5c9a-3145-4768-8024-5a7feb92b91a",
        "rating": 1,
        "comment": ""
    }
]